aiot_studio-1.0.3.dist-info/DESCRIPTION.rst
aiot_studio-1.0.3.dist-info/METADATA
aiot_studio-1.0.3.dist-info/RECORD
aiot_studio-1.0.3.dist-info/WHEEL
aiot_studio-1.0.3.dist-info/metadata.json
aiot_studio-1.0.3.dist-info/top_level.txt
aiotstudio/__init__.py
aiotstudio/datasource.py
aiotstudio/_core/__init__.py
aiotstudio/_core/client.py
aiotstudio/_core/errors.py
aiotstudio/_core/logger.py
aiotstudio/_core/services.py
aiotstudio/_core/types.py
