Metadata-Version: 2.0
Name: aiot-studio
Version: 1.0.3
Summary: UNKNOWN
Home-page: https://smartobjects.mnubo.com/documentation/sdks.html
Author: mnubo, inc.
Author-email: support@mnubo.com
License: UNKNOWN
Platform: UNKNOWN
Requires-Dist: numpy
Requires-Dist: pandas (>=0.20.3)
Requires-Dist: requests
